violation/__init__.py
violation/admin.py
violation/apps.py
violation/signals.py
violation/tests.py
violation/behaviours/__init__.py
violation/behaviours/rule.py
violation/behaviours/violation.py
violation/fields/__init__.py
violation/fields/rule.py
violation/forms/__init__.py
violation/forms/violation.py
violation/managers/__init__.py
violation/managers/rule.py
violation/managers/violation.py
violation/migrations/0001_initial.py
violation/migrations/0002_alter_rule_id_alter_violation_id.py
violation/migrations/__init__.py
violation/models/__init__.py
violation/models/rule.py
violation/models/violation.py
violation/viewmixins/__init__.py
violation/viewmixins/violation.py
violation/views/__init__.py
violation/views/violation.py
django_violation-1.2.1.dist-info/LICENSE
django_violation-1.2.1.dist-info/METADATA
django_violation-1.2.1.dist-info/WHEEL
django_violation-1.2.1.dist-info/top_level.txt
django_violation-1.2.1.dist-info/RECORD
