Metadata-Version: 2.1
Name: django-violation
Version: 1.2.1
Summary: django-violation is a reusable Django application for reporting illicit/improper acts.
Home-page: https://github.com/adepeter/django-violations
Author: Peter Oluwaseun
Author-email: adepeter26@gmail.com
License: MIT
Project-URL: Source, https://github.com/adepeter/django-violations
Project-URL: Tracker, https://github.com/adepeter/django-violations/issues
Classifier: Development Status :: 5 - Production/Stable
Classifier: Environment :: Web Environment
Classifier: Framework :: Django
Classifier: Framework :: Django :: 3.0
Classifier: Framework :: Django :: 3.1
Classifier: Framework :: Django :: 4.0
Classifier: Framework :: Django :: 4.1
Classifier: Intended Audience :: Developers
Classifier: License :: OSI Approved :: MIT License
Classifier: Operating System :: OS Independent
Classifier: Programming Language :: Python
Classifier: Programming Language :: Python :: 3
Classifier: Programming Language :: Python :: 3 :: Only
Classifier: Programming Language :: Python :: 3.6
Classifier: Programming Language :: Python :: 3.7
Classifier: Programming Language :: Python :: 3.8
Classifier: Programming Language :: Python :: 3.9
Classifier: Programming Language :: Python :: 3.10
Requires-Python: >=3.7
License-File: LICENSE
Requires-Dist: Django (>=3.1)
